markplot.py
markplot-0.1.3.dist-info/DESCRIPTION.rst
markplot-0.1.3.dist-info/METADATA
markplot-0.1.3.dist-info/RECORD
markplot-0.1.3.dist-info/WHEEL
markplot-0.1.3.dist-info/entry_points.txt
markplot-0.1.3.dist-info/metadata.json
markplot-0.1.3.dist-info/top_level.txt
