Metadata-Version: 2.0
Name: markplot
Version: 0.1.3
Summary: Simple script generating plots and csv file from your project's journals
Home-page: https://github.com/groovytron/markplot
Author: Julien M'Poy
Author-email: julien.mpoy@he-arc.ch
License: GPL-3.0+
Keywords: overview feedback work
Platform: UNKNOWN
Classifier: Development Status :: 3 - Alpha
Classifier: Intended Audience :: Other Audience
Classifier: License :: OSI Approved :: GNU General Public License v3 or later (GPLv3+)
Classifier: Programming Language :: Python :: 3.6
Requires-Python: >=3
Requires-Dist: Click
Requires-Dist: numpy
Requires-Dist: matplotlib
